ostorlab/__init__.py
ostorlab/configuration_manager.py
ostorlab/exceptions.py
ostorlab/main.py
ostorlab/py.typed
ostorlab/agent/__init__.py
ostorlab/agent/agent.py
ostorlab/agent/definitions.py
ostorlab/agent/kb/__init__.py
ostorlab/agent/kb/kb.py
ostorlab/agent/kb/KB/README.md
ostorlab/agent/kb/KB/MOBILE_CLIENT/ANDROID/_HARDENING/APK_DEBUG/description.md
ostorlab/agent/kb/KB/MOBILE_CLIENT/ANDROID/_HARDENING/APK_DEBUG/meta.json
ostorlab/agent/kb/KB/MOBILE_CLIENT/ANDROID/_HARDENING/APK_DEBUG/recommendation.md
ostorlab/agent/kb/KB/MOBILE_CLIENT/ANDROID/_HARDENING/APK_ELF_NOTPROTECTED/description.md
ostorlab/agent/kb/KB/MOBILE_CLIENT/ANDROID/_HARDENING/APK_ELF_NOTPROTECTED/meta.json
ostorlab/agent/kb/KB/MOBILE_CLIENT/ANDROID/_HARDENING/APK_ELF_NOTPROTECTED/recommendation.md
ostorlab/agent/kb/KB/MOBILE_CLIENT/ANDROID/_HARDENING/APK_INSECURE_NETWORK_SECURITY_CONFIG/description.md
ostorlab/agent/kb/KB/MOBILE_CLIENT/ANDROID/_HARDENING/APK_INSECURE_NETWORK_SECURITY_CONFIG/meta.json
ostorlab/agent/kb/KB/MOBILE_CLIENT/ANDROID/_HARDENING/APK_INSECURE_NETWORK_SECURITY_CONFIG/recommendation.md
ostorlab/agent/kb/KB/MOBILE_CLIENT/ANDROID/_HARDENING/APK_NOT_OBFUSCATED/description.md
ostorlab/agent/kb/KB/MOBILE_CLIENT/ANDROID/_HARDENING/APK_NOT_OBFUSCATED/meta.json
ostorlab/agent/kb/KB/MOBILE_CLIENT/ANDROID/_HARDENING/APK_NOT_OBFUSCATED/recommendation.md
ostorlab/agent/kb/KB/MOBILE_CLIENT/ANDROID/_HIGH/APK_FILE_PROVIDER_PERMISSIVE_EXTERNAL_PATH/description.md
ostorlab/agent/kb/KB/MOBILE_CLIENT/ANDROID/_HIGH/APK_FILE_PROVIDER_PERMISSIVE_EXTERNAL_PATH/meta.json
ostorlab/agent/kb/KB/MOBILE_CLIENT/ANDROID/_HIGH/APK_FILE_PROVIDER_PERMISSIVE_EXTERNAL_PATH/recommendation.md
ostorlab/agent/kb/KB/MOBILE_CLIENT/ANDROID/_HIGH/APK_INSECURE_EXEC_CMD/description.md
ostorlab/agent/kb/KB/MOBILE_CLIENT/ANDROID/_HIGH/APK_INSECURE_EXEC_CMD/meta.json
ostorlab/agent/kb/KB/MOBILE_CLIENT/ANDROID/_HIGH/APK_INSECURE_EXEC_CMD/recommendation.md
ostorlab-1.0.19.dist-info/LICENSE
ostorlab-1.0.19.dist-info/METADATA
ostorlab-1.0.19.dist-info/WHEEL
ostorlab-1.0.19.dist-info/entry_points.txt
ostorlab-1.0.19.dist-info/top_level.txt
ostorlab-1.0.19.dist-info/RECORD
