Metadata-Version: 2.1
Name: ostorlab
Version: 1.0.19
Summary: OXO Scanner Orchestrator for the Modern Age.
Home-page: https://github.com/Ostorlab/ostorlab
Author: Ostorlab
Author-email: oxo@ostorlab.dev
License: Apache-2.0
Project-URL: Documentation, https://oxo.ostorlab.co/
Project-URL: Source, https://github.com/Ostorlab/oxo
Project-URL: Changelog, https://github.com/Ostorlab/oxo/releases
Project-URL: Tracker, https://github.com/Ostorlab/oxo/issues
Project-URL: Twitter, https://twitter.com/OstorlabSec
Platform: any
Classifier: Development Status :: 4 - Beta
Classifier: Programming Language :: Python
Requires-Python: >=3.9
License-File: LICENSE
Requires-Dist: click
Requires-Dist: docker
Requires-Dist: jsonschema >=4.4.0
Requires-Dist: protobuf ==3.20.1
Requires-Dist: httpx
Requires-Dist: rich
Requires-Dist: ruamel.yaml
Requires-Dist: tenacity
Requires-Dist: sqlalchemy ~=1.4
Requires-Dist: semver >=3.0.0
Requires-Dist: markdownify
Requires-Dist: alembic
Requires-Dist: py-ubjson
Requires-Dist: nats-py
Requires-Dist: requests <=2.26.0
Requires-Dist: importlib-metadata ; python_version < "3.8"
Provides-Extra: agent
Requires-Dist: Werkzeug ~=2.3 ; extra == 'agent'
Requires-Dist: aio-pika ; extra == 'agent'
Requires-Dist: flask ; extra == 'agent'
Requires-Dist: redis ; extra == 'agent'
Requires-Dist: google-cloud-logging ; extra == 'agent'
Requires-Dist: opentelemetry-distro ; extra == 'agent'
Requires-Dist: opentelemetry-exporter-jaeger ; extra == 'agent'
Requires-Dist: opentelemetry-exporter-gcp-trace ; extra == 'agent'
Provides-Extra: google-cloud-logging
Requires-Dist: google-cloud-logging ; extra == 'google-cloud-logging'
Provides-Extra: scanner
Requires-Dist: psutil ; extra == 'scanner'
Requires-Dist: python-daemon ; extra == 'scanner'
Provides-Extra: serve
Requires-Dist: flask ; extra == 'serve'
Requires-Dist: graphene-file-upload ; extra == 'serve'
Requires-Dist: flask-graphql ; extra == 'serve'
Requires-Dist: graphene-sqlalchemy ; extra == 'serve'
Requires-Dist: cvss ; extra == 'serve'
Requires-Dist: flask-cors ; extra == 'serve'
Provides-Extra: testing
Requires-Dist: setuptools ; extra == 'testing'
Requires-Dist: pytest ; extra == 'testing'
Requires-Dist: pytest-cov ; extra == 'testing'
Requires-Dist: pytest-asyncio ; extra == 'testing'
Requires-Dist: pytest-mock ; extra == 'testing'
Requires-Dist: pytest-timeout ; extra == 'testing'
Requires-Dist: pytest-httpx ; extra == 'testing'
